odoo/addons/account_invoice_overdue_warn_sale/README.rst
odoo/addons/account_invoice_overdue_warn_sale/__init__.py
odoo/addons/account_invoice_overdue_warn_sale/__manifest__.py
odoo/addons/account_invoice_overdue_warn_sale/i18n/account_invoice_overdue_warn_sale.pot
odoo/addons/account_invoice_overdue_warn_sale/i18n/ca.po
odoo/addons/account_invoice_overdue_warn_sale/i18n/es.po
odoo/addons/account_invoice_overdue_warn_sale/i18n/fr.po
odoo/addons/account_invoice_overdue_warn_sale/i18n/it.po
odoo/addons/account_invoice_overdue_warn_sale/i18n/pt_BR.po
odoo/addons/account_invoice_overdue_warn_sale/models/__init__.py
odoo/addons/account_invoice_overdue_warn_sale/models/sale_order.py
odoo/addons/account_invoice_overdue_warn_sale/readme/CONTRIBUTORS.md
odoo/addons/account_invoice_overdue_warn_sale/readme/DESCRIPTION.md
odoo/addons/account_invoice_overdue_warn_sale/static/description/icon.png
odoo/addons/account_invoice_overdue_warn_sale/static/description/index.html
odoo/addons/account_invoice_overdue_warn_sale/static/description/sale_order_overdue_invoice_warn.png
odoo/addons/account_invoice_overdue_warn_sale/views/sale_order.xml
odoo_addon_account_invoice_overdue_warn_sale-18.0.1.0.0.2.dist-info/METADATA
odoo_addon_account_invoice_overdue_warn_sale-18.0.1.0.0.2.dist-info/WHEEL
odoo_addon_account_invoice_overdue_warn_sale-18.0.1.0.0.2.dist-info/top_level.txt
odoo_addon_account_invoice_overdue_warn_sale-18.0.1.0.0.2.dist-info/RECORD
