Metadata-Version: 2.1
Name: odoo-addon-account_invoice_overdue_warn_sale
Version: 18.0.1.0.0.2
Requires-Python: >=3.10
Requires-Dist: odoo-addon-account_invoice_overdue_warn==18.0.*
Requires-Dist: odoo==18.0.*
Summary: Show overdue warning on sale order form view
Home-page: https://github.com/OCA/credit-control
License: AGPL-3
Author: Akretion,Odoo Community Association (OCA)
Author-email: support@odoo-community.org
Classifier: Programming Language :: Python
Classifier: Framework :: Odoo
Classifier: Framework :: Odoo :: 18.0
Classifier: License :: OSI Approved :: GNU Affero General Public License v3
